toyapp/__init__.py
toyapp/cli.py
toyapp/toyapp.py
toyapp-0.1.2.dist-info/AUTHORS.rst
toyapp-0.1.2.dist-info/LICENSE
toyapp-0.1.2.dist-info/METADATA
toyapp-0.1.2.dist-info/WHEEL
toyapp-0.1.2.dist-info/entry_points.txt
toyapp-0.1.2.dist-info/top_level.txt
toyapp-0.1.2.dist-info/RECORD
