Metadata-Version: 2.1
Name: toyapp
Version: 0.1.2
Summary: Experiment with cookiecutter and docker to create a toyapp
Home-page: https://github.com/ian1roberts/toyapp
Author: Ian Roberts
Author-email: ian1blog@icloud.com
License: MIT license
Keywords: toyapp
Classifier: Development Status :: 2 - Pre-Alpha
Classifier: Intended Audience :: Developers
Classifier: License :: OSI Approved :: MIT License
Classifier: Natural Language :: English
Classifier: Programming Language :: Python :: 3
Classifier: Programming Language :: Python :: 3.6
Classifier: Programming Language :: Python :: 3.7
Classifier: Programming Language :: Python :: 3.8
Requires-Python: >=3.6
License-File: LICENSE
License-File: AUTHORS.rst
Requires-Dist: Click >=7.0
